{"comments":null,"declarations":[{"children":[{"comments":null,"info":{"declType":"typeClassMember","type":{"annotation":[],"contents":{"identifier":"a","kind":null,"skolem":null,"type":{"annotation":[],"contents":{"identifier":"b","kind":null,"skolem":null,"type":{"annotation":[],"contents":{"identifier":"c","kind":null,"skolem":null,"type":{"annotation":[],"contents":[{"annotation":[],"contents":[{"annotation":[],"contents":[["Prim"],"Function"],"tag":"TypeConstructor"},{"annotation":[],"contents":{"annotation":[],"contents":[{"annotation":[],"contents":[{"annotation":[],"contents":[["Prim"],"Function"],"tag":"TypeConstructor"},{"annotation":[],"contents":"a","tag":"TypeVar"}],"tag":"TypeApp"},{"annotation":[],"contents":[{"annotation":[],"contents":[{"annotation":[],"contents":[["Prim"],"Function"],"tag":"TypeConstructor"},{"annotation":[],"contents":"c","tag":"TypeVar"}],"tag":"TypeApp"},{"annotation":[],"contents":"c","tag":"TypeVar"}],"tag":"TypeApp"}],"tag":"TypeApp"},"tag":"ParensInType"}],"tag":"TypeApp"},{"annotation":[],"contents":[{"annotation":[],"contents":[{"annotation":[],"contents":[["Prim"],"Function"],"tag":"TypeConstructor"},{"annotation":[],"contents":{"annotation":[],"contents":[{"annotation":[],"contents":[{"annotation":[],"contents":[["Prim"],"Function"],"tag":"TypeConstructor"},{"annotation":[],"contents":"b","tag":"TypeVar"}],"tag":"TypeApp"},{"annotation":[],"contents":[{"annotation":[],"contents":[{"annotation":[],"contents":[["Prim"],"Function"],"tag":"TypeConstructor"},{"annotation":[],"contents":"c","tag":"TypeVar"}],"tag":"TypeApp"},{"annotation":[],"contents":"c","tag":"TypeVar"}],"tag":"TypeApp"}],"tag":"TypeApp"},"tag":"ParensInType"}],"tag":"TypeApp"},{"annotation":[],"contents":[{"annotation":[],"contents":[{"annotation":[],"contents":[["Prim"],"Function"],"tag":"TypeConstructor"},{"annotation":[],"contents":"c","tag":"TypeVar"}],"tag":"TypeApp"},{"annotation":[],"contents":[{"annotation":[],"contents":[{"annotation":[],"contents":[["Prim"],"Function"],"tag":"TypeConstructor"},{"annotation":[],"contents":[{"annotation":[],"contents":[{"annotation":[],"contents":"p","tag":"TypeVar"},{"annotation":[],"contents":"a","tag":"TypeVar"}],"tag":"TypeApp"},{"annotation":[],"contents":"b","tag":"TypeVar"}],"tag":"TypeApp"}],"tag":"TypeApp"},{"annotation":[],"contents":"c","tag":"TypeVar"}],"tag":"TypeApp"}],"tag":"TypeApp"}],"tag":"TypeApp"}],"tag":"TypeApp"},"visibility":"TypeVarInvisible"},"tag":"ForAll"},"visibility":"TypeVarInvisible"},"tag":"ForAll"},"visibility":"TypeVarInvisible"},"tag":"ForAll"}},"sourceSpan":{"end":[38,77],"name":".spago/packages/foldable-traversable-6.0.0/src/Data/Bifoldable.purs","start":[38,3]},"title":"bifoldr"},{"comments":null,"info":{"declType":"typeClassMember","type":{"annotation":[],"contents":{"identifier":"a","kind":null,"skolem":null,"type":{"annotation":[],"contents":{"identifier":"b","kind":null,"skolem":null,"type":{"annotation":[],"contents":{"identifier":"c","kind":null,"skolem":null,"type":{"annotation":[],"contents":[{"annotation":[],"contents":[{"annotation":[],"contents":[["Prim"],"Function"],"tag":"TypeConstructor"},{"annotation":[],"contents":{"annotation":[],"contents":[{"annotation":[],"contents":[{"annotation":[],"contents":[["Prim"],"Function"],"tag":"TypeConstructor"},{"annotation":[],"contents":"c","tag":"TypeVar"}],"tag":"TypeApp"},{"annotation":[],"contents":[{"annotation":[],"contents":[{"annotation":[],"contents":[["Prim"],"Function"],"tag":"TypeConstructor"},{"annotation":[],"contents":"a","tag":"TypeVar"}],"tag":"TypeApp"},{"annotation":[],"contents":"c","tag":"TypeVar"}],"tag":"TypeApp"}],"tag":"TypeApp"},"tag":"ParensInType"}],"tag":"TypeApp"},{"annotation":[],"contents":[{"annotation":[],"contents":[{"annotation":[],"contents":[["Prim"],"Function"],"tag":"TypeConstructor"},{"annotation":[],"contents":{"annotation":[],"contents":[{"annotation":[],"contents":[{"annotation":[],"contents":[["Prim"],"Function"],"tag":"TypeConstructor"},{"annotation":[],"contents":"c","tag":"TypeVar"}],"tag":"TypeApp"},{"annotation":[],"contents":[{"annotation":[],"contents":[{"annotation":[],"contents":[["Prim"],"Function"],"tag":"TypeConstructor"},{"annotation":[],"contents":"b","tag":"TypeVar"}],"tag":"TypeApp"},{"annotation":[],"contents":"c","tag":"TypeVar"}],"tag":"TypeApp"}],"tag":"TypeApp"},"tag":"ParensInType"}],"tag":"TypeApp"},{"annotation":[],"contents":[{"annotation":[],"contents":[{"annotation":[],"contents":[["Prim"],"Function"],"tag":"TypeConstructor"},{"annotation":[],"contents":"c","tag":"TypeVar"}],"tag":"TypeApp"},{"annotation":[],"contents":[{"annotation":[],"contents":[{"annotation":[],"contents":[["Prim"],"Function"],"tag":"TypeConstructor"},{"annotation":[],"contents":[{"annotation":[],"contents":[{"annotation":[],"contents":"p","tag":"TypeVar"},{"annotation":[],"contents":"a","tag":"TypeVar"}],"tag":"TypeApp"},{"annotation":[],"contents":"b","tag":"TypeVar"}],"tag":"TypeApp"}],"tag":"TypeApp"},{"annotation":[],"contents":"c","tag":"TypeVar"}],"tag":"TypeApp"}],"tag":"TypeApp"}],"tag":"TypeApp"}],"tag":"TypeApp"},"visibility":"TypeVarInvisible"},"tag":"ForAll"},"visibility":"TypeVarInvisible"},"tag":"ForAll"},"visibility":"TypeVarInvisible"},"tag":"ForAll"}},"sourceSpan":{"end":[39,77],"name":".spago/packages/foldable-traversable-6.0.0/src/Data/Bifoldable.purs","start":[39,3]},"title":"bifoldl"},{"comments":null,"info":{"declType":"typeClassMember","type":{"annotation":[],"contents":{"identifier":"m","kind":null,"skolem":null,"type":{"annotation":[],"contents":{"identifier":"a","kind":null,"skolem":null,"type":{"annotation":[],"contents":{"identifier":"b","kind":null,"skolem":null,"type":{"annotation":[],"contents":[{"constraintAnn":[],"constraintArgs":[{"annotation":[],"contents":"m","tag":"TypeVar"}],"constraintClass":[["Data","Monoid"],"Monoid"],"constraintData":null,"constraintKindArgs":[]},{"annotation":[],"contents":[{"annotation":[],"contents":[{"annotation":[],"contents":[["Prim"],"Function"],"tag":"TypeConstructor"},{"annotation":[],"contents":{"annotation":[],"contents":[{"annotation":[],"contents":[{"annotation":[],"contents":[["Prim"],"Function"],"tag":"TypeConstructor"},{"annotation":[],"contents":"a","tag":"TypeVar"}],"tag":"TypeApp"},{"annotation":[],"contents":"m","tag":"TypeVar"}],"tag":"TypeApp"},"tag":"ParensInType"}],"tag":"TypeApp"},{"annotation":[],"contents":[{"annotation":[],"contents":[{"annotation":[],"contents":[["Prim"],"Function"],"tag":"TypeConstructor"},{"annotation":[],"contents":{"annotation":[],"contents":[{"annotation":[],"contents":[{"annotation":[],"contents":[["Prim"],"Function"],"tag":"TypeConstructor"},{"annotation":[],"contents":"b","tag":"TypeVar"}],"tag":"TypeApp"},{"annotation":[],"contents":"m","tag":"TypeVar"}],"tag":"TypeApp"},"tag":"ParensInType"}],"tag":"TypeApp"},{"annotation":[],"contents":[{"annotation":[],"contents":[{"annotation":[],"contents":[["Prim"],"Function"],"tag":"TypeConstructor"},{"annotation":[],"contents":[{"annotation":[],"contents":[{"annotation":[],"contents":"p","tag":"TypeVar"},{"annotation":[],"contents":"a","tag":"TypeVar"}],"tag":"TypeApp"},{"annotation":[],"contents":"b","tag":"TypeVar"}],"tag":"TypeApp"}],"tag":"TypeApp"},{"annotation":[],"contents":"m","tag":"TypeVar"}],"tag":"TypeApp"}],"tag":"TypeApp"}],"tag":"TypeApp"}],"tag":"ConstrainedType"},"visibility":"TypeVarInvisible"},"tag":"ForAll"},"visibility":"TypeVarInvisible"},"tag":"ForAll"},"visibility":"TypeVarInvisible"},"tag":"ForAll"}},"sourceSpan":{"end":[40,76],"name":".spago/packages/foldable-traversable-6.0.0/src/Data/Bifoldable.purs","start":[40,3]},"title":"bifoldMap"},{"comments":null,"info":{"declType":"instance","dependencies":[{"constraintAnn":[],"constraintArgs":[{"annotation":[],"contents":"f","tag":"TypeVar"}],"constraintClass":[["Data","Foldable"],"Foldable"],"constraintData":null,"constraintKindArgs":[]}],"type":{"annotation":[],"contents":[{"annotation":[],"contents":[["Data","Bifoldable"],"Bifoldable"],"tag":"TypeConstructor"},{"annotation":[],"contents":[{"annotation":[],"contents":[["Data","Functor","Clown"],"Clown"],"tag":"TypeConstructor"},{"annotation":[],"contents":"f","tag":"TypeVar"}],"tag":"TypeApp"}],"tag":"TypeApp"}},"sourceSpan":{"end":[45,40],"name":".spago/packages/foldable-traversable-6.0.0/src/Data/Bifoldable.purs","start":[42,1]},"title":"bifoldableClown"},{"comments":null,"info":{"declType":"instance","dependencies":[{"constraintAnn":[],"constraintArgs":[{"annotation":[],"contents":"f","tag":"TypeVar"}],"constraintClass":[["Data","Foldable"],"Foldable"],"constraintData":null,"constraintKindArgs":[]}],"type":{"annotation":[],"contents":[{"annotation":[],"contents":[["Data","Bifoldable"],"Bifoldable"],"tag":"TypeConstructor"},{"annotation":[],"contents":[{"annotation":[],"contents":[["Data","Functor","Joker"],"Joker"],"tag":"TypeConstructor"},{"annotation":[],"contents":"f","tag":"TypeVar"}],"tag":"TypeApp"}],"tag":"TypeApp"}},"sourceSpan":{"end":[50,40],"name":".spago/packages/foldable-traversable-6.0.0/src/Data/Bifoldable.purs","start":[47,1]},"title":"bifoldableJoker"},{"comments":null,"info":{"declType":"instance","dependencies":[{"constraintAnn":[],"constraintArgs":[{"annotation":[],"contents":"p","tag":"TypeVar"}],"constraintClass":[["Data","Bifoldable"],"Bifoldable"],"constraintData":null,"constraintKindArgs":[]}],"type":{"annotation":[],"contents":[{"annotation":[],"contents":[["Data","Bifoldable"],"Bifoldable"],"tag":"TypeConstructor"},{"annotation":[],"contents":[{"annotation":[],"contents":[["Data","Functor","Flip"],"Flip"],"tag":"TypeConstructor"},{"annotation":[],"contents":"p","tag":"TypeVar"}],"tag":"TypeApp"}],"tag":"TypeApp"}},"sourceSpan":{"end":[55,43],"name":".spago/packages/foldable-traversable-6.0.0/src/Data/Bifoldable.purs","start":[52,1]},"title":"bifoldableFlip"},{"comments":null,"info":{"declType":"instance","dependencies":[{"constraintAnn":[],"constraintArgs":[{"annotation":[],"contents":"f","tag":"TypeVar"}],"constraintClass":[["Data","Bifoldable"],"Bifoldable"],"constraintData":null,"constraintKindArgs":[]},{"constraintAnn":[],"constraintArgs":[{"annotation":[],"contents":"g","tag":"TypeVar"}],"constraintClass":[["Data","Bifoldable"],"Bifoldable"],"constraintData":null,"constraintKindArgs":[]}],"type":{"annotation":[],"contents":[{"annotation":[],"contents":[["Data","Bifoldable"],"Bifoldable"],"tag":"TypeConstructor"},{"annotation":[],"contents":[{"annotation":[],"contents":[{"annotation":[],"contents":[["Data","Functor","Product2"],"Product2"],"tag":"TypeConstructor"},{"annotation":[],"contents":"f","tag":"TypeVar"}],"tag":"TypeApp"},{"annotation":[],"contents":"g","tag":"TypeVar"}],"tag":"TypeApp"}],"tag":"TypeApp"}},"sourceSpan":{"end":[60,68],"name":".spago/packages/foldable-traversable-6.0.0/src/Data/Bifoldable.purs","start":[57,1]},"title":"bifoldableProduct2"},{"comments":null,"info":{"declType":"instance","dependencies":[],"type":{"annotation":[],"contents":[{"annotation":[],"contents":[["Data","Bifoldable"],"Bifoldable"],"tag":"TypeConstructor"},{"annotation":[],"contents":[["Data","Either"],"Either"],"tag":"TypeConstructor"}],"tag":"TypeApp"}},"sourceSpan":{"end":[68,32],"name":".spago/packages/foldable-traversable-6.0.0/src/Data/Bifoldable.purs","start":[62,1]},"title":"bifoldableEither"},{"comments":null,"info":{"declType":"instance","dependencies":[],"type":{"annotation":[],"contents":[{"annotation":[],"contents":[["Data","Bifoldable"],"Bifoldable"],"tag":"TypeConstructor"},{"annotation":[],"contents":[["Data","Tuple"],"Tuple"],"tag":"TypeConstructor"}],"tag":"TypeApp"}},"sourceSpan":{"end":[73,42],"name":".spago/packages/foldable-traversable-6.0.0/src/Data/Bifoldable.purs","start":[70,1]},"title":"bifoldableTuple"},{"comments":null,"info":{"declType":"instance","dependencies":[],"type":{"annotation":[],"contents":[{"annotation":[],"contents":[["Data","Bifoldable"],"Bifoldable"],"tag":"TypeConstructor"},{"annotation":[],"contents":[["Data","Const"],"Const"],"tag":"TypeConstructor"}],"tag":"TypeApp"}},"sourceSpan":{"end":[78,32],"name":".spago/packages/foldable-traversable-6.0.0/src/Data/Bifoldable.purs","start":[75,1]},"title":"bifoldableConst"}],"comments":"`Bifoldable` represents data structures with two type arguments which can be\nfolded.\n\nA fold for such a structure requires two step functions, one for each type\nargument. Type class instances should choose the appropriate step function based\non the type of the element encountered at each point of the fold.\n\nDefault implementations are provided by the following functions:\n\n- `bifoldrDefault`\n- `bifoldlDefault`\n- `bifoldMapDefaultR`\n- `bifoldMapDefaultL`\n\nNote: some combinations of the default implementations are unsafe to\nuse together - causing a non-terminating mutually recursive cycle.\nThese combinations are documented per function.\n","info":{"arguments":[["p",null]],"declType":"typeClass","fundeps":[],"superclasses":[]},"kind":{"keyword":"class","kind":{"annotation":[],"contents":[{"annotation":[],"contents":[{"annotation":[],"contents":[["Prim"],"Function"],"tag":"TypeConstructor"},{"annotation":[],"contents":[{"annotation":[],"contents":[{"annotation":[],"contents":[["Prim"],"Function"],"tag":"TypeConstructor"},{"annotation":[],"contents":[["Prim"],"Type"],"tag":"TypeConstructor"}],"tag":"TypeApp"},{"annotation":[],"contents":[{"annotation":[],"contents":[{"annotation":[],"contents":[["Prim"],"Function"],"tag":"TypeConstructor"},{"annotation":[],"contents":[["Prim"],"Type"],"tag":"TypeConstructor"}],"tag":"TypeApp"},{"annotation":[],"contents":[["Prim"],"Type"],"tag":"TypeConstructor"}],"tag":"TypeApp"}],"tag":"TypeApp"}],"tag":"TypeApp"},{"annotation":[],"contents":[["Prim"],"Constraint"],"tag":"TypeConstructor"}],"tag":"TypeApp"}},"sourceSpan":{"end":[40,76],"name":".spago/packages/foldable-traversable-6.0.0/src/Data/Bifoldable.purs","start":[37,1]},"title":"Bifoldable"},{"children":[],"comments":"A default implementation of `bifoldr` using `bifoldMap`.\n\nNote: when defining a `Bifoldable` instance, this function is unsafe to\nuse in combination with `bifoldMapDefaultR`.\n","info":{"declType":"value","type":{"annotation":[],"contents":{"identifier":"p","kind":null,"skolem":null,"type":{"annotation":[],"contents":{"identifier":"a","kind":null,"skolem":null,"type":{"annotation":[],"contents":{"identifier":"b","kind":null,"skolem":null,"type":{"annotation":[],"contents":{"identifier":"c","kind":null,"skolem":null,"type":{"annotation":[],"contents":[{"constraintAnn":[],"constraintArgs":[{"annotation":[],"contents":"p","tag":"TypeVar"}],"constraintClass":[["Data","Bifoldable"],"Bifoldable"],"constraintData":null,"constraintKindArgs":[]},{"annotation":[],"contents":[{"annotation":[],"contents":[{"annotation":[],"contents":[["Prim"],"Function"],"tag":"TypeConstructor"},{"annotation":[],"contents":{"annotation":[],"contents":[{"annotation":[],"contents":[{"annotation":[],"contents":[["Prim"],"Function"],"tag":"TypeConstructor"},{"annotation":[],"contents":"a","tag":"TypeVar"}],"tag":"TypeApp"},{"annotation":[],"contents":[{"annotation":[],"contents":[{"annotation":[],"contents":[["Prim"],"Function"],"tag":"TypeConstructor"},{"annotation":[],"contents":"c","tag":"TypeVar"}],"tag":"TypeApp"},{"annotation":[],"contents":"c","tag":"TypeVar"}],"tag":"TypeApp"}],"tag":"TypeApp"},"tag":"ParensInType"}],"tag":"TypeApp"},{"annotation":[],"contents":[{"annotation":[],"contents":[{"annotation":[],"contents":[["Prim"],"Function"],"tag":"TypeConstructor"},{"annotation":[],"contents":{"annotation":[],"contents":[{"annotation":[],"contents":[{"annotation":[],"contents":[["Prim"],"Function"],"tag":"TypeConstructor"},{"annotation":[],"contents":"b","tag":"TypeVar"}],"tag":"TypeApp"},{"annotation":[],"contents":[{"annotation":[],"contents":[{"annotation":[],"contents":[["Prim"],"Function"],"tag":"TypeConstructor"},{"annotation":[],"contents":"c","tag":"TypeVar"}],"tag":"TypeApp"},{"annotation":[],"contents":"c","tag":"TypeVar"}],"tag":"TypeApp"}],"tag":"TypeApp"},"tag":"ParensInType"}],"tag":"TypeApp"},{"annotation":[],"contents":[{"annotation":[],"contents":[{"annotation":[],"contents":[["Prim"],"Function"],"tag":"TypeConstructor"},{"annotation":[],"contents":"c","tag":"TypeVar"}],"tag":"TypeApp"},{"annotation":[],"contents":[{"annotation":[],"contents":[{"annotation":[],"contents":[["Prim"],"Function"],"tag":"TypeConstructor"},{"annotation":[],"contents":[{"annotation":[],"contents":[{"annotation":[],"contents":"p","tag":"TypeVar"},{"annotation":[],"contents":"a","tag":"TypeVar"}],"tag":"TypeApp"},{"annotation":[],"contents":"b","tag":"TypeVar"}],"tag":"TypeApp"}],"tag":"TypeApp"},{"annotation":[],"contents":"c","tag":"TypeVar"}],"tag":"TypeApp"}],"tag":"TypeApp"}],"tag":"TypeApp"}],"tag":"TypeApp"}],"tag":"ConstrainedType"},"visibility":"TypeVarInvisible"},"tag":"ForAll"},"visibility":"TypeVarInvisible"},"tag":"ForAll"},"visibility":"TypeVarInvisible"},"tag":"ForAll"},"visibility":"TypeVarInvisible"},"tag":"ForAll"}},"kind":null,"sourceSpan":{"end":[91,7],"name":".spago/packages/foldable-traversable-6.0.0/src/Data/Bifoldable.purs","start":[84,1]},"title":"bifoldrDefault"},{"children":[],"comments":"A default implementation of `bifoldl` using `bifoldMap`.\n\nNote: when defining a `Bifoldable` instance, this function is unsafe to\nuse in combination with `bifoldMapDefaultL`.\n","info":{"declType":"value","type":{"annotation":[],"contents":{"identifier":"p","kind":null,"skolem":null,"type":{"annotation":[],"contents":{"identifier":"a","kind":null,"skolem":null,"type":{"annotation":[],"contents":{"identifier":"b","kind":null,"skolem":null,"type":{"annotation":[],"contents":{"identifier":"c","kind":null,"skolem":null,"type":{"annotation":[],"contents":[{"constraintAnn":[],"constraintArgs":[{"annotation":[],"contents":"p","tag":"TypeVar"}],"constraintClass":[["Data","Bifoldable"],"Bifoldable"],"constraintData":null,"constraintKindArgs":[]},{"annotation":[],"contents":[{"annotation":[],"contents":[{"annotation":[],"contents":[["Prim"],"Function"],"tag":"TypeConstructor"},{"annotation":[],"contents":{"annotation":[],"contents":[{"annotation":[],"contents":[{"annotation":[],"contents":[["Prim"],"Function"],"tag":"TypeConstructor"},{"annotation":[],"contents":"c","tag":"TypeVar"}],"tag":"TypeApp"},{"annotation":[],"contents":[{"annotation":[],"contents":[{"annotation":[],"contents":[["Prim"],"Function"],"tag":"TypeConstructor"},{"annotation":[],"contents":"a","tag":"TypeVar"}],"tag":"TypeApp"},{"annotation":[],"contents":"c","tag":"TypeVar"}],"tag":"TypeApp"}],"tag":"TypeApp"},"tag":"ParensInType"}],"tag":"TypeApp"},{"annotation":[],"contents":[{"annotation":[],"contents":[{"annotation":[],"contents":[["Prim"],"Function"],"tag":"TypeConstructor"},{"annotation":[],"contents":{"annotation":[],"contents":[{"annotation":[],"contents":[{"annotation":[],"contents":[["Prim"],"Function"],"tag":"TypeConstructor"},{"annotation":[],"contents":"c","tag":"TypeVar"}],"tag":"TypeApp"},{"annotation":[],"contents":[{"annotation":[],"contents":[{"annotation":[],"contents":[["Prim"],"Function"],"tag":"TypeConstructor"},{"annotation":[],"contents":"b","tag":"TypeVar"}],"tag":"TypeApp"},{"annotation":[],"contents":"c","tag":"TypeVar"}],"tag":"TypeApp"}],"tag":"TypeApp"},"tag":"ParensInType"}],"tag":"TypeApp"},{"annotation":[],"contents":[{"annotation":[],"contents":[{"annotation":[],"contents":[["Prim"],"Function"],"tag":"TypeConstructor"},{"annotation":[],"contents":"c","tag":"TypeVar"}],"tag":"TypeApp"},{"annotation":[],"contents":[{"annotation":[],"contents":[{"annotation":[],"contents":[["Prim"],"Function"],"tag":"TypeConstructor"},{"annotation":[],"contents":[{"annotation":[],"contents":[{"annotation":[],"contents":"p","tag":"TypeVar"},{"annotation":[],"contents":"a","tag":"TypeVar"}],"tag":"TypeApp"},{"annotation":[],"contents":"b","tag":"TypeVar"}],"tag":"TypeApp"}],"tag":"TypeApp"},{"annotation":[],"contents":"c","tag":"TypeVar"}],"tag":"TypeApp"}],"tag":"TypeApp"}],"tag":"TypeApp"}],"tag":"TypeApp"}],"tag":"ConstrainedType"},"visibility":"TypeVarInvisible"},"tag":"ForAll"},"visibility":"TypeVarInvisible"},"tag":"ForAll"},"visibility":"TypeVarInvisible"},"tag":"ForAll"},"visibility":"TypeVarInvisible"},"tag":"ForAll"}},"kind":null,"sourceSpan":{"end":[105,7],"name":".spago/packages/foldable-traversable-6.0.0/src/Data/Bifoldable.purs","start":[98,1]},"title":"bifoldlDefault"},{"children":[],"comments":"A default implementation of `bifoldMap` using `bifoldr`.\n\nNote: when defining a `Bifoldable` instance, this function is unsafe to\nuse in combination with `bifoldrDefault`.\n","info":{"declType":"value","type":{"annotation":[],"contents":{"identifier":"p","kind":null,"skolem":null,"type":{"annotation":[],"contents":{"identifier":"m","kind":null,"skolem":null,"type":{"annotation":[],"contents":{"identifier":"a","kind":null,"skolem":null,"type":{"annotation":[],"contents":{"identifier":"b","kind":null,"skolem":null,"type":{"annotation":[],"contents":[{"constraintAnn":[],"constraintArgs":[{"annotation":[],"contents":"p","tag":"TypeVar"}],"constraintClass":[["Data","Bifoldable"],"Bifoldable"],"constraintData":null,"constraintKindArgs":[]},{"annotation":[],"contents":[{"constraintAnn":[],"constraintArgs":[{"annotation":[],"contents":"m","tag":"TypeVar"}],"constraintClass":[["Data","Monoid"],"Monoid"],"constraintData":null,"constraintKindArgs":[]},{"annotation":[],"contents":[{"annotation":[],"contents":[{"annotation":[],"contents":[["Prim"],"Function"],"tag":"TypeConstructor"},{"annotation":[],"contents":{"annotation":[],"contents":[{"annotation":[],"contents":[{"annotation":[],"contents":[["Prim"],"Function"],"tag":"TypeConstructor"},{"annotation":[],"contents":"a","tag":"TypeVar"}],"tag":"TypeApp"},{"annotation":[],"contents":"m","tag":"TypeVar"}],"tag":"TypeApp"},"tag":"ParensInType"}],"tag":"TypeApp"},{"annotation":[],"contents":[{"annotation":[],"contents":[{"annotation":[],"contents":[["Prim"],"Function"],"tag":"TypeConstructor"},{"annotation":[],"contents":{"annotation":[],"contents":[{"annotation":[],"contents":[{"annotation":[],"contents":[["Prim"],"Function"],"tag":"TypeConstructor"},{"annotation":[],"contents":"b","tag":"TypeVar"}],"tag":"TypeApp"},{"annotation":[],"contents":"m","tag":"TypeVar"}],"tag":"TypeApp"},"tag":"ParensInType"}],"tag":"TypeApp"},{"annotation":[],"contents":[{"annotation":[],"contents":[{"annotation":[],"contents":[["Prim"],"Function"],"tag":"TypeConstructor"},{"annotation":[],"contents":[{"annotation":[],"contents":[{"annotation":[],"contents":"p","tag":"TypeVar"},{"annotation":[],"contents":"a","tag":"TypeVar"}],"tag":"TypeApp"},{"annotation":[],"contents":"b","tag":"TypeVar"}],"tag":"TypeApp"}],"tag":"TypeApp"},{"annotation":[],"contents":"m","tag":"TypeVar"}],"tag":"TypeApp"}],"tag":"TypeApp"}],"tag":"TypeApp"}],"tag":"ConstrainedType"}],"tag":"ConstrainedType"},"visibility":"TypeVarInvisible"},"tag":"ForAll"},"visibility":"TypeVarInvisible"},"tag":"ForAll"},"visibility":"TypeVarInvisible"},"tag":"ForAll"},"visibility":"TypeVarInvisible"},"tag":"ForAll"}},"kind":null,"sourceSpan":{"end":[123,7],"name":".spago/packages/foldable-traversable-6.0.0/src/Data/Bifoldable.purs","start":[116,1]},"title":"bifoldMapDefaultR"},{"children":[],"comments":"A default implementation of `bifoldMap` using `bifoldl`.\n\nNote: when defining a `Bifoldable` instance, this function is unsafe to\nuse in combination with `bifoldlDefault`.\n","info":{"declType":"value","type":{"annotation":[],"contents":{"identifier":"p","kind":null,"skolem":null,"type":{"annotation":[],"contents":{"identifier":"m","kind":null,"skolem":null,"type":{"annotation":[],"contents":{"identifier":"a","kind":null,"skolem":null,"type":{"annotation":[],"contents":{"identifier":"b","kind":null,"skolem":null,"type":{"annotation":[],"contents":[{"constraintAnn":[],"constraintArgs":[{"annotation":[],"contents":"p","tag":"TypeVar"}],"constraintClass":[["Data","Bifoldable"],"Bifoldable"],"constraintData":null,"constraintKindArgs":[]},{"annotation":[],"contents":[{"constraintAnn":[],"constraintArgs":[{"annotation":[],"contents":"m","tag":"TypeVar"}],"constraintClass":[["Data","Monoid"],"Monoid"],"constraintData":null,"constraintKindArgs":[]},{"annotation":[],"contents":[{"annotation":[],"contents":[{"annotation":[],"contents":[["Prim"],"Function"],"tag":"TypeConstructor"},{"annotation":[],"contents":{"annotation":[],"contents":[{"annotation":[],"contents":[{"annotation":[],"contents":[["Prim"],"Function"],"tag":"TypeConstructor"},{"annotation":[],"contents":"a","tag":"TypeVar"}],"tag":"TypeApp"},{"annotation":[],"contents":"m","tag":"TypeVar"}],"tag":"TypeApp"},"tag":"ParensInType"}],"tag":"TypeApp"},{"annotation":[],"contents":[{"annotation":[],"contents":[{"annotation":[],"contents":[["Prim"],"Function"],"tag":"TypeConstructor"},{"annotation":[],"contents":{"annotation":[],"contents":[{"annotation":[],"contents":[{"annotation":[],"contents":[["Prim"],"Function"],"tag":"TypeConstructor"},{"annotation":[],"contents":"b","tag":"TypeVar"}],"tag":"TypeApp"},{"annotation":[],"contents":"m","tag":"TypeVar"}],"tag":"TypeApp"},"tag":"ParensInType"}],"tag":"TypeApp"},{"annotation":[],"contents":[{"annotation":[],"contents":[{"annotation":[],"contents":[["Prim"],"Function"],"tag":"TypeConstructor"},{"annotation":[],"contents":[{"annotation":[],"contents":[{"annotation":[],"contents":"p","tag":"TypeVar"},{"annotation":[],"contents":"a","tag":"TypeVar"}],"tag":"TypeApp"},{"annotation":[],"contents":"b","tag":"TypeVar"}],"tag":"TypeApp"}],"tag":"TypeApp"},{"annotation":[],"contents":"m","tag":"TypeVar"}],"tag":"TypeApp"}],"tag":"TypeApp"}],"tag":"TypeApp"}],"tag":"ConstrainedType"}],"tag":"ConstrainedType"},"visibility":"TypeVarInvisible"},"tag":"ForAll"},"visibility":"TypeVarInvisible"},"tag":"ForAll"},"visibility":"TypeVarInvisible"},"tag":"ForAll"},"visibility":"TypeVarInvisible"},"tag":"ForAll"}},"kind":null,"sourceSpan":{"end":[137,7],"name":".spago/packages/foldable-traversable-6.0.0/src/Data/Bifoldable.purs","start":[130,1]},"title":"bifoldMapDefaultL"},{"children":[],"comments":"Fold a data structure, accumulating values in a monoidal type.\n","info":{"declType":"value","type":{"annotation":[],"contents":{"identifier":"t","kind":null,"skolem":null,"type":{"annotation":[],"contents":{"identifier":"m","kind":null,"skolem":null,"type":{"annotation":[],"contents":[{"constraintAnn":[],"constraintArgs":[{"annotation":[],"contents":"t","tag":"TypeVar"}],"constraintClass":[["Data","Bifoldable"],"Bifoldable"],"constraintData":null,"constraintKindArgs":[]},{"annotation":[],"contents":[{"constraintAnn":[],"constraintArgs":[{"annotation":[],"contents":"m","tag":"TypeVar"}],"constraintClass":[["Data","Monoid"],"Monoid"],"constraintData":null,"constraintKindArgs":[]},{"annotation":[],"contents":[{"annotation":[],"contents":[{"annotation":[],"contents":[["Prim"],"Function"],"tag":"TypeConstructor"},{"annotation":[],"contents":[{"annotation":[],"contents":[{"annotation":[],"contents":"t","tag":"TypeVar"},{"annotation":[],"contents":"m","tag":"TypeVar"}],"tag":"TypeApp"},{"annotation":[],"contents":"m","tag":"TypeVar"}],"tag":"TypeApp"}],"tag":"TypeApp"},{"annotation":[],"contents":"m","tag":"TypeVar"}],"tag":"TypeApp"}],"tag":"ConstrainedType"}],"tag":"ConstrainedType"},"visibility":"TypeVarInvisible"},"tag":"ForAll"},"visibility":"TypeVarInvisible"},"tag":"ForAll"}},"kind":null,"sourceSpan":{"end":[142,61],"name":".spago/packages/foldable-traversable-6.0.0/src/Data/Bifoldable.purs","start":[142,1]},"title":"bifold"},{"children":[],"comments":"Traverse a data structure, accumulating effects using an `Applicative` functor,\nignoring the final result.\n","info":{"declType":"value","type":{"annotation":[],"contents":{"identifier":"t","kind":null,"skolem":null,"type":{"annotation":[],"contents":{"identifier":"f","kind":null,"skolem":null,"type":{"annotation":[],"contents":{"identifier":"a","kind":null,"skolem":null,"type":{"annotation":[],"contents":{"identifier":"b","kind":null,"skolem":null,"type":{"annotation":[],"contents":{"identifier":"c","kind":null,"skolem":null,"type":{"annotation":[],"contents":{"identifier":"d","kind":null,"skolem":null,"type":{"annotation":[],"contents":[{"constraintAnn":[],"constraintArgs":[{"annotation":[],"contents":"t","tag":"TypeVar"}],"constraintClass":[["Data","Bifoldable"],"Bifoldable"],"constraintData":null,"constraintKindArgs":[]},{"annotation":[],"contents":[{"constraintAnn":[],"constraintArgs":[{"annotation":[],"contents":"f","tag":"TypeVar"}],"constraintClass":[["Control","Applicative"],"Applicative"],"constraintData":null,"constraintKindArgs":[]},{"annotation":[],"contents":[{"annotation":[],"contents":[{"annotation":[],"contents":[["Prim"],"Function"],"tag":"TypeConstructor"},{"annotation":[],"contents":{"annotation":[],"contents":[{"annotation":[],"contents":[{"annotation":[],"contents":[["Prim"],"Function"],"tag":"TypeConstructor"},{"annotation":[],"contents":"a","tag":"TypeVar"}],"tag":"TypeApp"},{"annotation":[],"contents":[{"annotation":[],"contents":"f","tag":"TypeVar"},{"annotation":[],"contents":"c","tag":"TypeVar"}],"tag":"TypeApp"}],"tag":"TypeApp"},"tag":"ParensInType"}],"tag":"TypeApp"},{"annotation":[],"contents":[{"annotation":[],"contents":[{"annotation":[],"contents":[["Prim"],"Function"],"tag":"TypeConstructor"},{"annotation":[],"contents":{"annotation":[],"contents":[{"annotation":[],"contents":[{"annotation":[],"contents":[["Prim"],"Function"],"tag":"TypeConstructor"},{"annotation":[],"contents":"b","tag":"TypeVar"}],"tag":"TypeApp"},{"annotation":[],"contents":[{"annotation":[],"contents":"f","tag":"TypeVar"},{"annotation":[],"contents":"d","tag":"TypeVar"}],"tag":"TypeApp"}],"tag":"TypeApp"},"tag":"ParensInType"}],"tag":"TypeApp"},{"annotation":[],"contents":[{"annotation":[],"contents":[{"annotation":[],"contents":[["Prim"],"Function"],"tag":"TypeConstructor"},{"annotation":[],"contents":[{"annotation":[],"contents":[{"annotation":[],"contents":"t","tag":"TypeVar"},{"annotation":[],"contents":"a","tag":"TypeVar"}],"tag":"TypeApp"},{"annotation":[],"contents":"b","tag":"TypeVar"}],"tag":"TypeApp"}],"tag":"TypeApp"},{"annotation":[],"contents":[{"annotation":[],"contents":"f","tag":"TypeVar"},{"annotation":[],"contents":[["Data","Unit"],"Unit"],"tag":"TypeConstructor"}],"tag":"TypeApp"}],"tag":"TypeApp"}],"tag":"TypeApp"}],"tag":"TypeApp"}],"tag":"ConstrainedType"}],"tag":"ConstrainedType"},"visibility":"TypeVarInvisible"},"tag":"ForAll"},"visibility":"TypeVarInvisible"},"tag":"ForAll"},"visibility":"TypeVarInvisible"},"tag":"ForAll"},"visibility":"TypeVarInvisible"},"tag":"ForAll"},"visibility":"TypeVarInvisible"},"tag":"ForAll"},"visibility":"TypeVarInvisible"},"tag":"ForAll"}},"kind":null,"sourceSpan":{"end":[154,12],"name":".spago/packages/foldable-traversable-6.0.0/src/Data/Bifoldable.purs","start":[147,1]},"title":"bitraverse_"},{"children":[],"comments":"A version of `bitraverse_` with the data structure as the first argument.\n","info":{"declType":"value","type":{"annotation":[],"contents":{"identifier":"t","kind":null,"skolem":null,"type":{"annotation":[],"contents":{"identifier":"f","kind":null,"skolem":null,"type":{"annotation":[],"contents":{"identifier":"a","kind":null,"skolem":null,"type":{"annotation":[],"contents":{"identifier":"b","kind":null,"skolem":null,"type":{"annotation":[],"contents":{"identifier":"c","kind":null,"skolem":null,"type":{"annotation":[],"contents":{"identifier":"d","kind":null,"skolem":null,"type":{"annotation":[],"contents":[{"constraintAnn":[],"constraintArgs":[{"annotation":[],"contents":"t","tag":"TypeVar"}],"constraintClass":[["Data","Bifoldable"],"Bifoldable"],"constraintData":null,"constraintKindArgs":[]},{"annotation":[],"contents":[{"constraintAnn":[],"constraintArgs":[{"annotation":[],"contents":"f","tag":"TypeVar"}],"constraintClass":[["Control","Applicative"],"Applicative"],"constraintData":null,"constraintKindArgs":[]},{"annotation":[],"contents":[{"annotation":[],"contents":[{"annotation":[],"contents":[["Prim"],"Function"],"tag":"TypeConstructor"},{"annotation":[],"contents":[{"annotation":[],"contents":[{"annotation":[],"contents":"t","tag":"TypeVar"},{"annotation":[],"contents":"a","tag":"TypeVar"}],"tag":"TypeApp"},{"annotation":[],"contents":"b","tag":"TypeVar"}],"tag":"TypeApp"}],"tag":"TypeApp"},{"annotation":[],"contents":[{"annotation":[],"contents":[{"annotation":[],"contents":[["Prim"],"Function"],"tag":"TypeConstructor"},{"annotation":[],"contents":{"annotation":[],"contents":[{"annotation":[],"contents":[{"annotation":[],"contents":[["Prim"],"Function"],"tag":"TypeConstructor"},{"annotation":[],"contents":"a","tag":"TypeVar"}],"tag":"TypeApp"},{"annotation":[],"contents":[{"annotation":[],"contents":"f","tag":"TypeVar"},{"annotation":[],"contents":"c","tag":"TypeVar"}],"tag":"TypeApp"}],"tag":"TypeApp"},"tag":"ParensInType"}],"tag":"TypeApp"},{"annotation":[],"contents":[{"annotation":[],"contents":[{"annotation":[],"contents":[["Prim"],"Function"],"tag":"TypeConstructor"},{"annotation":[],"contents":{"annotation":[],"contents":[{"annotation":[],"contents":[{"annotation":[],"contents":[["Prim"],"Function"],"tag":"TypeConstructor"},{"annotation":[],"contents":"b","tag":"TypeVar"}],"tag":"TypeApp"},{"annotation":[],"contents":[{"annotation":[],"contents":"f","tag":"TypeVar"},{"annotation":[],"contents":"d","tag":"TypeVar"}],"tag":"TypeApp"}],"tag":"TypeApp"},"tag":"ParensInType"}],"tag":"TypeApp"},{"annotation":[],"contents":[{"annotation":[],"contents":"f","tag":"TypeVar"},{"annotation":[],"contents":[["Data","Unit"],"Unit"],"tag":"TypeConstructor"}],"tag":"TypeApp"}],"tag":"TypeApp"}],"tag":"TypeApp"}],"tag":"TypeApp"}],"tag":"ConstrainedType"}],"tag":"ConstrainedType"},"visibility":"TypeVarInvisible"},"tag":"ForAll"},"visibility":"TypeVarInvisible"},"tag":"ForAll"},"visibility":"TypeVarInvisible"},"tag":"ForAll"},"visibility":"TypeVarInvisible"},"tag":"ForAll"},"visibility":"TypeVarInvisible"},"tag":"ForAll"},"visibility":"TypeVarInvisible"},"tag":"ForAll"}},"kind":null,"sourceSpan":{"end":[165,12],"name":".spago/packages/foldable-traversable-6.0.0/src/Data/Bifoldable.purs","start":[158,1]},"title":"bifor_"},{"children":[],"comments":"Collapse a data structure, collecting effects using an `Applicative` functor,\nignoring the final result.\n","info":{"declType":"value","type":{"annotation":[],"contents":{"identifier":"t","kind":null,"skolem":null,"type":{"annotation":[],"contents":{"identifier":"f","kind":null,"skolem":null,"type":{"annotation":[],"contents":{"identifier":"a","kind":null,"skolem":null,"type":{"annotation":[],"contents":{"identifier":"b","kind":null,"skolem":null,"type":{"annotation":[],"contents":[{"constraintAnn":[],"constraintArgs":[{"annotation":[],"contents":"t","tag":"TypeVar"}],"constraintClass":[["Data","Bifoldable"],"Bifoldable"],"constraintData":null,"constraintKindArgs":[]},{"annotation":[],"contents":[{"constraintAnn":[],"constraintArgs":[{"annotation":[],"contents":"f","tag":"TypeVar"}],"constraintClass":[["Control","Applicative"],"Applicative"],"constraintData":null,"constraintKindArgs":[]},{"annotation":[],"contents":[{"annotation":[],"contents":[{"annotation":[],"contents":[["Prim"],"Function"],"tag":"TypeConstructor"},{"annotation":[],"contents":[{"annotation":[],"contents":[{"annotation":[],"contents":"t","tag":"TypeVar"},{"annotation":[],"contents":{"annotation":[],"contents":[{"annotation":[],"contents":"f","tag":"TypeVar"},{"annotation":[],"contents":"a","tag":"TypeVar"}],"tag":"TypeApp"},"tag":"ParensInType"}],"tag":"TypeApp"},{"annotation":[],"contents":{"annotation":[],"contents":[{"annotation":[],"contents":"f","tag":"TypeVar"},{"annotation":[],"contents":"b","tag":"TypeVar"}],"tag":"TypeApp"},"tag":"ParensInType"}],"tag":"TypeApp"}],"tag":"TypeApp"},{"annotation":[],"contents":[{"annotation":[],"contents":"f","tag":"TypeVar"},{"annotation":[],"contents":[["Data","Unit"],"Unit"],"tag":"TypeConstructor"}],"tag":"TypeApp"}],"tag":"TypeApp"}],"tag":"ConstrainedType"}],"tag":"ConstrainedType"},"visibility":"TypeVarInvisible"},"tag":"ForAll"},"visibility":"TypeVarInvisible"},"tag":"ForAll"},"visibility":"TypeVarInvisible"},"tag":"ForAll"},"visibility":"TypeVarInvisible"},"tag":"ForAll"}},"kind":null,"sourceSpan":{"end":[175,12],"name":".spago/packages/foldable-traversable-6.0.0/src/Data/Bifoldable.purs","start":[170,1]},"title":"bisequence_"},{"children":[],"comments":"Test whether a predicate holds at any position in a data structure.\n","info":{"declType":"value","type":{"annotation":[],"contents":{"identifier":"t","kind":null,"skolem":null,"type":{"annotation":[],"contents":{"identifier":"a","kind":null,"skolem":null,"type":{"annotation":[],"contents":{"identifier":"b","kind":null,"skolem":null,"type":{"annotation":[],"contents":{"identifier":"c","kind":null,"skolem":null,"type":{"annotation":[],"contents":[{"constraintAnn":[],"constraintArgs":[{"annotation":[],"contents":"t","tag":"TypeVar"}],"constraintClass":[["Data","Bifoldable"],"Bifoldable"],"constraintData":null,"constraintKindArgs":[]},{"annotation":[],"contents":[{"constraintAnn":[],"constraintArgs":[{"annotation":[],"contents":"c","tag":"TypeVar"}],"constraintClass":[["Data","BooleanAlgebra"],"BooleanAlgebra"],"constraintData":null,"constraintKindArgs":[]},{"annotation":[],"contents":[{"annotation":[],"contents":[{"annotation":[],"contents":[["Prim"],"Function"],"tag":"TypeConstructor"},{"annotation":[],"contents":{"annotation":[],"contents":[{"annotation":[],"contents":[{"annotation":[],"contents":[["Prim"],"Function"],"tag":"TypeConstructor"},{"annotation":[],"contents":"a","tag":"TypeVar"}],"tag":"TypeApp"},{"annotation":[],"contents":"c","tag":"TypeVar"}],"tag":"TypeApp"},"tag":"ParensInType"}],"tag":"TypeApp"},{"annotation":[],"contents":[{"annotation":[],"contents":[{"annotation":[],"contents":[["Prim"],"Function"],"tag":"TypeConstructor"},{"annotation":[],"contents":{"annotation":[],"contents":[{"annotation":[],"contents":[{"annotation":[],"contents":[["Prim"],"Function"],"tag":"TypeConstructor"},{"annotation":[],"contents":"b","tag":"TypeVar"}],"tag":"TypeApp"},{"annotation":[],"contents":"c","tag":"TypeVar"}],"tag":"TypeApp"},"tag":"ParensInType"}],"tag":"TypeApp"},{"annotation":[],"contents":[{"annotation":[],"contents":[{"annotation":[],"contents":[["Prim"],"Function"],"tag":"TypeConstructor"},{"annotation":[],"contents":[{"annotation":[],"contents":[{"annotation":[],"contents":"t","tag":"TypeVar"},{"annotation":[],"contents":"a","tag":"TypeVar"}],"tag":"TypeApp"},{"annotation":[],"contents":"b","tag":"TypeVar"}],"tag":"TypeApp"}],"tag":"TypeApp"},{"annotation":[],"contents":"c","tag":"TypeVar"}],"tag":"TypeApp"}],"tag":"TypeApp"}],"tag":"TypeApp"}],"tag":"ConstrainedType"}],"tag":"ConstrainedType"},"visibility":"TypeVarInvisible"},"tag":"ForAll"},"visibility":"TypeVarInvisible"},"tag":"ForAll"},"visibility":"TypeVarInvisible"},"tag":"ForAll"},"visibility":"TypeVarInvisible"},"tag":"ForAll"}},"kind":null,"sourceSpan":{"end":[186,7],"name":".spago/packages/foldable-traversable-6.0.0/src/Data/Bifoldable.purs","start":[179,1]},"title":"biany"},{"children":[],"comments":"Test whether a predicate holds at all positions in a data structure.\n","info":{"declType":"value","type":{"annotation":[],"contents":{"identifier":"t","kind":null,"skolem":null,"type":{"annotation":[],"contents":{"identifier":"a","kind":null,"skolem":null,"type":{"annotation":[],"contents":{"identifier":"b","kind":null,"skolem":null,"type":{"annotation":[],"contents":{"identifier":"c","kind":null,"skolem":null,"type":{"annotation":[],"contents":[{"constraintAnn":[],"constraintArgs":[{"annotation":[],"contents":"t","tag":"TypeVar"}],"constraintClass":[["Data","Bifoldable"],"Bifoldable"],"constraintData":null,"constraintKindArgs":[]},{"annotation":[],"contents":[{"constraintAnn":[],"constraintArgs":[{"annotation":[],"contents":"c","tag":"TypeVar"}],"constraintClass":[["Data","BooleanAlgebra"],"BooleanAlgebra"],"constraintData":null,"constraintKindArgs":[]},{"annotation":[],"contents":[{"annotation":[],"contents":[{"annotation":[],"contents":[["Prim"],"Function"],"tag":"TypeConstructor"},{"annotation":[],"contents":{"annotation":[],"contents":[{"annotation":[],"contents":[{"annotation":[],"contents":[["Prim"],"Function"],"tag":"TypeConstructor"},{"annotation":[],"contents":"a","tag":"TypeVar"}],"tag":"TypeApp"},{"annotation":[],"contents":"c","tag":"TypeVar"}],"tag":"TypeApp"},"tag":"ParensInType"}],"tag":"TypeApp"},{"annotation":[],"contents":[{"annotation":[],"contents":[{"annotation":[],"contents":[["Prim"],"Function"],"tag":"TypeConstructor"},{"annotation":[],"contents":{"annotation":[],"contents":[{"annotation":[],"contents":[{"annotation":[],"contents":[["Prim"],"Function"],"tag":"TypeConstructor"},{"annotation":[],"contents":"b","tag":"TypeVar"}],"tag":"TypeApp"},{"annotation":[],"contents":"c","tag":"TypeVar"}],"tag":"TypeApp"},"tag":"ParensInType"}],"tag":"TypeApp"},{"annotation":[],"contents":[{"annotation":[],"contents":[{"annotation":[],"contents":[["Prim"],"Function"],"tag":"TypeConstructor"},{"annotation":[],"contents":[{"annotation":[],"contents":[{"annotation":[],"contents":"t","tag":"TypeVar"},{"annotation":[],"contents":"a","tag":"TypeVar"}],"tag":"TypeApp"},{"annotation":[],"contents":"b","tag":"TypeVar"}],"tag":"TypeApp"}],"tag":"TypeApp"},{"annotation":[],"contents":"c","tag":"TypeVar"}],"tag":"TypeApp"}],"tag":"TypeApp"}],"tag":"TypeApp"}],"tag":"ConstrainedType"}],"tag":"ConstrainedType"},"visibility":"TypeVarInvisible"},"tag":"ForAll"},"visibility":"TypeVarInvisible"},"tag":"ForAll"},"visibility":"TypeVarInvisible"},"tag":"ForAll"},"visibility":"TypeVarInvisible"},"tag":"ForAll"}},"kind":null,"sourceSpan":{"end":[197,7],"name":".spago/packages/foldable-traversable-6.0.0/src/Data/Bifoldable.purs","start":[190,1]},"title":"biall"}],"name":"Data.Bifoldable","reExports":[]}