{"builtWith":"0.15.10","comments":[],"decls":[{"annotation":{"meta":null,"sourceSpan":{"end":[0,0],"start":[0,0]}},"bindType":"NonRec","expression":{"abstraction":{"annotation":{"meta":{"metaType":"IsForeign"},"sourceSpan":{"end":[20,73],"start":[20,71]}},"type":"Var","value":{"identifier":"conj","moduleName":["Data","HeytingAlgebra"]}},"annotation":{"meta":{"metaType":"IsSyntheticApp"},"sourceSpan":{"end":[20,79],"start":[20,65]}},"argument":{"annotation":{"meta":null,"sourceSpan":{"end":[0,0],"start":[0,0]}},"type":"Var","value":{"identifier":"heytingAlgebraBoolean","moduleName":["Data","HeytingAlgebra"]}},"type":"App"},"identifier":"conj"},{"annotation":{"meta":null,"sourceSpan":{"end":[0,0],"start":[0,0]}},"bindType":"NonRec","expression":{"abstraction":{"annotation":{"meta":{"metaType":"IsForeign"},"sourceSpan":{"end":[31,69],"start":[31,67]}},"type":"Var","value":{"identifier":"eq","moduleName":["Data","Eq"]}},"annotation":{"meta":{"metaType":"IsSyntheticApp"},"sourceSpan":{"end":[31,72],"start":[31,61]}},"argument":{"annotation":{"meta":null,"sourceSpan":{"end":[0,0],"start":[0,0]}},"type":"Var","value":{"identifier":"eqOrdering","moduleName":["Data","Ordering"]}},"type":"App"},"identifier":"eq"},{"annotation":{"meta":null,"sourceSpan":{"end":[12,56],"start":[12,1]}},"bindType":"NonRec","expression":{"annotation":{"meta":{"metaType":"IsNewtype"},"sourceSpan":{"end":[12,56],"start":[12,1]}},"argument":"x","body":{"annotation":{"meta":null,"sourceSpan":{"end":[12,56],"start":[12,1]}},"type":"Var","value":{"identifier":"x","sourcePos":[0,0]}},"type":"Abs"},"identifier":"Equivalence"},{"annotation":{"meta":null,"sourceSpan":{"end":[20,80],"start":[19,1]}},"bindType":"NonRec","expression":{"abstraction":{"annotation":{"meta":{"metaType":"IsNewtype"},"sourceSpan":{"end":[20,80],"start":[19,1]}},"type":"Var","value":{"identifier":"Semigroup$Dict","moduleName":["Data","Semigroup"]}},"annotation":{"meta":null,"sourceSpan":{"end":[20,80],"start":[19,1]}},"argument":{"annotation":{"meta":null,"sourceSpan":{"end":[20,80],"start":[19,1]}},"type":"Literal","value":{"literalType":"ObjectLiteral","value":[["append",{"annotation":{"meta":null,"sourceSpan":{"end":[20,80],"start":[19,1]}},"argument":"v","body":{"annotation":{"meta":null,"sourceSpan":{"end":[20,80],"start":[19,1]}},"argument":"v1","body":{"annotation":{"meta":null,"sourceSpan":{"end":[20,80],"start":[19,1]}},"caseAlternatives":[{"binders":[{"annotation":{"meta":{"metaType":"IsNewtype"},"sourceSpan":{"end":[20,24],"start":[20,11]}},"binderType":"ConstructorBinder","binders":[{"annotation":{"meta":null,"sourceSpan":{"end":[20,24],"start":[20,23]}},"binderType":"VarBinder","identifier":"p"}],"constructorName":{"identifier":"Equivalence","moduleName":["Data","Equivalence"]},"typeName":{"identifier":"Equivalence","moduleName":["Data","Equivalence"]}},{"annotation":{"meta":{"metaType":"IsNewtype"},"sourceSpan":{"end":[20,40],"start":[20,27]}},"binderType":"ConstructorBinder","binders":[{"annotation":{"meta":null,"sourceSpan":{"end":[20,40],"start":[20,39]}},"binderType":"VarBinder","identifier":"q"}],"constructorName":{"identifier":"Equivalence","moduleName":["Data","Equivalence"]},"typeName":{"identifier":"Equivalence","moduleName":["Data","Equivalence"]}}],"expression":{"abstraction":{"annotation":{"meta":{"metaType":"IsNewtype"},"sourceSpan":{"end":[20,55],"start":[20,44]}},"type":"Var","value":{"identifier":"Equivalence","moduleName":["Data","Equivalence"]}},"annotation":{"meta":null,"sourceSpan":{"end":[20,80],"start":[20,44]}},"argument":{"annotation":{"meta":null,"sourceSpan":{"end":[20,79],"start":[20,57]}},"argument":"a","body":{"annotation":{"meta":null,"sourceSpan":{"end":[20,79],"start":[20,57]}},"argument":"b","body":{"abstraction":{"abstraction":{"annotation":{"meta":null,"sourceSpan":{"end":[0,0],"start":[0,0]}},"type":"Var","value":{"identifier":"conj","moduleName":["Data","Equivalence"]}},"annotation":{"meta":null,"sourceSpan":{"end":[20,79],"start":[20,65]}},"argument":{"abstraction":{"abstraction":{"annotation":{"meta":null,"sourceSpan":{"end":[20,66],"start":[20,65]}},"type":"Var","value":{"identifier":"p","sourcePos":[20,23]}},"annotation":{"meta":null,"sourceSpan":{"end":[20,68],"start":[20,65]}},"argument":{"annotation":{"meta":null,"sourceSpan":{"end":[20,68],"start":[20,67]}},"type":"Var","value":{"identifier":"a","sourcePos":[20,58]}},"type":"App"},"annotation":{"meta":null,"sourceSpan":{"end":[20,70],"start":[20,65]}},"argument":{"annotation":{"meta":null,"sourceSpan":{"end":[20,70],"start":[20,69]}},"type":"Var","value":{"identifier":"b","sourcePos":[20,60]}},"type":"App"},"type":"App"},"annotation":{"meta":null,"sourceSpan":{"end":[20,79],"start":[20,65]}},"argument":{"abstraction":{"abstraction":{"annotation":{"meta":null,"sourceSpan":{"end":[20,75],"start":[20,74]}},"type":"Var","value":{"identifier":"q","sourcePos":[20,39]}},"annotation":{"meta":null,"sourceSpan":{"end":[20,77],"start":[20,74]}},"argument":{"annotation":{"meta":null,"sourceSpan":{"end":[20,77],"start":[20,76]}},"type":"Var","value":{"identifier":"a","sourcePos":[20,58]}},"type":"App"},"annotation":{"meta":null,"sourceSpan":{"end":[20,79],"start":[20,74]}},"argument":{"annotation":{"meta":null,"sourceSpan":{"end":[20,79],"start":[20,78]}},"type":"Var","value":{"identifier":"b","sourcePos":[20,60]}},"type":"App"},"type":"App"},"type":"Abs"},"type":"Abs"},"type":"App"},"isGuarded":false}],"caseExpressions":[{"annotation":{"meta":null,"sourceSpan":{"end":[20,80],"start":[20,3]}},"type":"Var","value":{"identifier":"v","sourcePos":[0,0]}},{"annotation":{"meta":null,"sourceSpan":{"end":[20,80],"start":[20,3]}},"type":"Var","value":{"identifier":"v1","sourcePos":[0,0]}}],"type":"Case"},"type":"Abs"},"type":"Abs"}]]}},"type":"App"},"identifier":"semigroupEquivalence"},{"annotation":{"meta":null,"sourceSpan":{"end":[14,64],"start":[14,1]}},"bindType":"NonRec","expression":{"abstraction":{"annotation":{"meta":{"metaType":"IsNewtype"},"sourceSpan":{"end":[14,64],"start":[14,1]}},"type":"Var","value":{"identifier":"Newtype$Dict","moduleName":["Data","Newtype"]}},"annotation":{"meta":null,"sourceSpan":{"end":[14,64],"start":[14,1]}},"argument":{"annotation":{"meta":null,"sourceSpan":{"end":[14,64],"start":[14,1]}},"type":"Literal","value":{"literalType":"ObjectLiteral","value":[["Coercible0",{"annotation":{"meta":null,"sourceSpan":{"end":[14,64],"start":[14,1]}},"argument":"$__unused","body":{"annotation":{"meta":null,"sourceSpan":{"end":[14,64],"start":[14,1]}},"type":"Var","value":{"identifier":"undefined","moduleName":["Prim"]}},"type":"Abs"}]]}},"type":"App"},"identifier":"newtypeEquivalence"},{"annotation":{"meta":null,"sourceSpan":{"end":[23,38],"start":[22,1]}},"bindType":"NonRec","expression":{"abstraction":{"annotation":{"meta":{"metaType":"IsNewtype"},"sourceSpan":{"end":[23,38],"start":[22,1]}},"type":"Var","value":{"identifier":"Monoid$Dict","moduleName":["Data","Monoid"]}},"annotation":{"meta":null,"sourceSpan":{"end":[23,38],"start":[22,1]}},"argument":{"annotation":{"meta":null,"sourceSpan":{"end":[23,38],"start":[22,1]}},"type":"Literal","value":{"literalType":"ObjectLiteral","value":[["mempty",{"abstraction":{"annotation":{"meta":{"metaType":"IsNewtype"},"sourceSpan":{"end":[23,23],"start":[23,12]}},"type":"Var","value":{"identifier":"Equivalence","moduleName":["Data","Equivalence"]}},"annotation":{"meta":null,"sourceSpan":{"end":[23,38],"start":[23,12]}},"argument":{"annotation":{"meta":null,"sourceSpan":{"end":[23,37],"start":[23,25]}},"argument":"v","body":{"annotation":{"meta":null,"sourceSpan":{"end":[23,37],"start":[23,25]}},"argument":"v1","body":{"annotation":{"meta":null,"sourceSpan":{"end":[23,37],"start":[23,33]}},"type":"Literal","value":{"literalType":"BooleanLiteral","value":true}},"type":"Abs"},"type":"Abs"},"type":"App"}],["Semigroup0",{"annotation":{"meta":null,"sourceSpan":{"end":[23,38],"start":[22,1]}},"argument":"$__unused","body":{"annotation":{"meta":null,"sourceSpan":{"end":[0,0],"start":[0,0]}},"type":"Var","value":{"identifier":"semigroupEquivalence","moduleName":["Data","Equivalence"]}},"type":"Abs"}]]}},"type":"App"},"identifier":"monoidEquivalence"},{"annotation":{"meta":null,"sourceSpan":{"end":[26,54],"start":[26,1]}},"bindType":"NonRec","expression":{"annotation":{"meta":null,"sourceSpan":{"end":[26,54],"start":[26,1]}},"argument":"dictEq","body":{"abstraction":{"annotation":{"meta":{"metaType":"IsNewtype"},"sourceSpan":{"end":[27,33],"start":[27,22]}},"type":"Var","value":{"identifier":"Equivalence","moduleName":["Data","Equivalence"]}},"annotation":{"meta":null,"sourceSpan":{"end":[27,36],"start":[27,22]}},"argument":{"abstraction":{"annotation":{"meta":{"metaType":"IsForeign"},"sourceSpan":{"end":[27,36],"start":[27,34]}},"type":"Var","value":{"identifier":"eq","moduleName":["Data","Eq"]}},"annotation":{"meta":{"metaType":"IsSyntheticApp"},"sourceSpan":{"end":[27,36],"start":[27,34]}},"argument":{"annotation":{"meta":null,"sourceSpan":{"end":[0,0],"start":[0,0]}},"type":"Var","value":{"identifier":"dictEq","sourcePos":[0,0]}},"type":"App"},"type":"App"},"type":"Abs"},"identifier":"defaultEquivalence"},{"annotation":{"meta":null,"sourceSpan":{"end":[17,50],"start":[16,1]}},"bindType":"NonRec","expression":{"abstraction":{"annotation":{"meta":{"metaType":"IsNewtype"},"sourceSpan":{"end":[17,50],"start":[16,1]}},"type":"Var","value":{"identifier":"Contravariant$Dict","moduleName":["Data","Functor","Contravariant"]}},"annotation":{"meta":null,"sourceSpan":{"end":[17,50],"start":[16,1]}},"argument":{"annotation":{"meta":null,"sourceSpan":{"end":[17,50],"start":[16,1]}},"type":"Literal","value":{"literalType":"ObjectLiteral","value":[["cmap",{"annotation":{"meta":null,"sourceSpan":{"end":[17,50],"start":[16,1]}},"argument":"f","body":{"annotation":{"meta":null,"sourceSpan":{"end":[17,50],"start":[16,1]}},"argument":"v","body":{"annotation":{"meta":null,"sourceSpan":{"end":[17,50],"start":[16,1]}},"caseAlternatives":[{"binders":[{"annotation":{"meta":null,"sourceSpan":{"end":[17,9],"start":[17,8]}},"binderType":"VarBinder","identifier":"f1"},{"annotation":{"meta":{"metaType":"IsNewtype"},"sourceSpan":{"end":[17,24],"start":[17,11]}},"binderType":"ConstructorBinder","binders":[{"annotation":{"meta":null,"sourceSpan":{"end":[17,24],"start":[17,23]}},"binderType":"VarBinder","identifier":"g"}],"constructorName":{"identifier":"Equivalence","moduleName":["Data","Equivalence"]},"typeName":{"identifier":"Equivalence","moduleName":["Data","Equivalence"]}}],"expression":{"abstraction":{"annotation":{"meta":{"metaType":"IsNewtype"},"sourceSpan":{"end":[17,39],"start":[17,28]}},"type":"Var","value":{"identifier":"Equivalence","moduleName":["Data","Equivalence"]}},"annotation":{"meta":null,"sourceSpan":{"end":[17,50],"start":[17,28]}},"argument":{"abstraction":{"abstraction":{"annotation":{"meta":{"metaType":"IsForeign"},"sourceSpan":{"end":[17,46],"start":[17,44]}},"type":"Var","value":{"identifier":"on","moduleName":["Data","Function"]}},"annotation":{"meta":null,"sourceSpan":{"end":[17,49],"start":[17,41]}},"argument":{"annotation":{"meta":null,"sourceSpan":{"end":[17,42],"start":[17,41]}},"type":"Var","value":{"identifier":"g","sourcePos":[17,23]}},"type":"App"},"annotation":{"meta":null,"sourceSpan":{"end":[17,49],"start":[17,41]}},"argument":{"annotation":{"meta":null,"sourceSpan":{"end":[17,49],"start":[17,48]}},"type":"Var","value":{"identifier":"f1","sourcePos":[17,8]}},"type":"App"},"type":"App"},"isGuarded":false}],"caseExpressions":[{"annotation":{"meta":null,"sourceSpan":{"end":[17,50],"start":[17,3]}},"type":"Var","value":{"identifier":"f","sourcePos":[17,8]}},{"annotation":{"meta":null,"sourceSpan":{"end":[17,50],"start":[17,3]}},"type":"Var","value":{"identifier":"v","sourcePos":[0,0]}}],"type":"Case"},"type":"Abs"},"type":"Abs"}]]}},"type":"App"},"identifier":"contravariantEquivalence"},{"annotation":{"meta":null,"sourceSpan":{"end":[30,65],"start":[30,1]}},"bindType":"NonRec","expression":{"annotation":{"meta":null,"sourceSpan":{"end":[30,65],"start":[30,1]}},"argument":"v","body":{"annotation":{"meta":null,"sourceSpan":{"end":[30,65],"start":[30,1]}},"caseAlternatives":[{"binders":[{"annotation":{"meta":{"metaType":"IsNewtype"},"sourceSpan":{"end":[31,36],"start":[31,24]}},"binderType":"ConstructorBinder","binders":[{"annotation":{"meta":null,"sourceSpan":{"end":[31,36],"start":[31,35]}},"binderType":"VarBinder","identifier":"p"}],"constructorName":{"identifier":"Comparison","moduleName":["Data","Comparison"]},"typeName":{"identifier":"Comparison","moduleName":["Data","Comparison"]}}],"expression":{"abstraction":{"annotation":{"meta":{"metaType":"IsNewtype"},"sourceSpan":{"end":[31,51],"start":[31,40]}},"type":"Var","value":{"identifier":"Equivalence","moduleName":["Data","Equivalence"]}},"annotation":{"meta":null,"sourceSpan":{"end":[31,73],"start":[31,40]}},"argument":{"annotation":{"meta":null,"sourceSpan":{"end":[31,72],"start":[31,53]}},"argument":"a","body":{"annotation":{"meta":null,"sourceSpan":{"end":[31,72],"start":[31,53]}},"argument":"b","body":{"abstraction":{"abstraction":{"annotation":{"meta":null,"sourceSpan":{"end":[0,0],"start":[0,0]}},"type":"Var","value":{"identifier":"eq","moduleName":["Data","Equivalence"]}},"annotation":{"meta":null,"sourceSpan":{"end":[31,72],"start":[31,61]}},"argument":{"abstraction":{"abstraction":{"annotation":{"meta":null,"sourceSpan":{"end":[31,62],"start":[31,61]}},"type":"Var","value":{"identifier":"p","sourcePos":[31,35]}},"annotation":{"meta":null,"sourceSpan":{"end":[31,64],"start":[31,61]}},"argument":{"annotation":{"meta":null,"sourceSpan":{"end":[31,64],"start":[31,63]}},"type":"Var","value":{"identifier":"a","sourcePos":[31,54]}},"type":"App"},"annotation":{"meta":null,"sourceSpan":{"end":[31,66],"start":[31,61]}},"argument":{"annotation":{"meta":null,"sourceSpan":{"end":[31,66],"start":[31,65]}},"type":"Var","value":{"identifier":"b","sourcePos":[31,56]}},"type":"App"},"type":"App"},"annotation":{"meta":null,"sourceSpan":{"end":[31,72],"start":[31,61]}},"argument":{"annotation":{"meta":{"constructorType":"SumType","identifiers":[],"metaType":"IsConstructor"},"sourceSpan":{"end":[31,72],"start":[31,70]}},"type":"Var","value":{"identifier":"EQ","moduleName":["Data","Ordering"]}},"type":"App"},"type":"Abs"},"type":"Abs"},"type":"App"},"isGuarded":false}],"caseExpressions":[{"annotation":{"meta":null,"sourceSpan":{"end":[31,73],"start":[31,1]}},"type":"Var","value":{"identifier":"v","sourcePos":[0,0]}}],"type":"Case"},"type":"Abs"},"identifier":"comparisonEquivalence"}],"exports":["Equivalence","defaultEquivalence","comparisonEquivalence","newtypeEquivalence","contravariantEquivalence","semigroupEquivalence","monoidEquivalence"],"foreign":[],"imports":[{"annotation":{"meta":null,"sourceSpan":{"end":[31,73],"start":[1,1]}},"moduleName":["Data","Comparison"]},{"annotation":{"meta":null,"sourceSpan":{"end":[31,73],"start":[1,1]}},"moduleName":["Data","Eq"]},{"annotation":{"meta":null,"sourceSpan":{"end":[31,73],"start":[1,1]}},"moduleName":["Data","Equivalence"]},{"annotation":{"meta":null,"sourceSpan":{"end":[31,73],"start":[1,1]}},"moduleName":["Data","Function"]},{"annotation":{"meta":null,"sourceSpan":{"end":[31,73],"start":[1,1]}},"moduleName":["Data","Functor","Contravariant"]},{"annotation":{"meta":null,"sourceSpan":{"end":[31,73],"start":[1,1]}},"moduleName":["Data","HeytingAlgebra"]},{"annotation":{"meta":null,"sourceSpan":{"end":[31,73],"start":[1,1]}},"moduleName":["Data","Monoid"]},{"annotation":{"meta":null,"sourceSpan":{"end":[31,73],"start":[1,1]}},"moduleName":["Data","Newtype"]},{"annotation":{"meta":null,"sourceSpan":{"end":[31,73],"start":[1,1]}},"moduleName":["Data","Ordering"]},{"annotation":{"meta":null,"sourceSpan":{"end":[31,73],"start":[1,1]}},"moduleName":["Data","Semigroup"]},{"annotation":{"meta":null,"sourceSpan":{"end":[3,15],"start":[3,1]}},"moduleName":["Prelude"]},{"annotation":{"meta":null,"sourceSpan":{"end":[31,73],"start":[1,1]}},"moduleName":["Prim"]}],"moduleName":["Data","Equivalence"],"modulePath":".spago/packages/contravariant-6.0.0/src/Data/Equivalence.purs","reExports":{},"sourceSpan":{"end":[31,73],"start":[1,1]}}